foxglove/__init__.py
foxglove/__main__.py
foxglove/asgi.py
foxglove/auth.py
foxglove/cli.py
foxglove/devtools.py
foxglove/exceptions.py
foxglove/logs.py
foxglove/main.py
foxglove/middleware.py
foxglove/recaptcha.py
foxglove/redis.py
foxglove/route_class.py
foxglove/settings.py
foxglove/templates.py
foxglove/utils.py
foxglove/version.py
foxglove/db/__init__.py
foxglove/db/helpers.py
foxglove/db/main.py
foxglove/db/middleware.py
foxglove/db/migrations.py
foxglove/db/patches.py
foxglove/db/utils.py
foxglove/testing/__init__.py
foxglove/testing/test_client.py
foxglove/testing/test_server.py
foxglove_web-0.0.39.dist-info/METADATA
foxglove_web-0.0.39.dist-info/WHEEL
foxglove_web-0.0.39.dist-info/licenses/LICENSE
foxglove_web-0.0.39.dist-info/RECORD
