Metadata-Version: 2.1
Name: foxglove-web
Version: 0.0.39
Summary: Tools for FastAPI
Project-URL: Homepage, https://github.com/samuelcolvin/foxglove
Project-URL: Funding, https://github.com/sponsors/samuelcolvin
Project-URL: Source, https://github.com/samuelcolvin/foxglove
Project-URL: Changelog, https://github.com/samuelcolvin/foxglove/releases
Author-email: Samuel Colvin <s@muelcolvin.com>
License: The MIT License (MIT)
License-File: LICENSE
Classifier: Development Status :: 4 - Beta
Classifier: Environment :: MacOS X
Classifier: Intended Audience :: Developers
Classifier: Intended Audience :: Information Technology
Classifier: Intended Audience :: System Administrators
Classifier: License :: OSI Approved :: MIT License
Classifier: Operating System :: POSIX :: Linux
Classifier: Operating System :: Unix
Classifier: Programming Language :: Python
Classifier: Programming Language :: Python :: 3
Classifier: Programming Language :: Python :: 3 :: Only
Classifier: Programming Language :: Python :: 3.8
Classifier: Programming Language :: Python :: 3.9
Classifier: Programming Language :: Python :: 3.10
Classifier: Programming Language :: Python :: 3.11
Classifier: Topic :: Internet
Requires-Python: >=3.8
Requires-Dist: aiodns>=3.0.0
Requires-Dist: arq>=0.23
Requires-Dist: asyncpg>=0.23.0
Requires-Dist: bcrypt>=4.0.1
Requires-Dist: buildpg>=0.3.0
Requires-Dist: fastapi>=0.101.0
Requires-Dist: httpx>=0.21.1
Requires-Dist: itsdangerous>=1.1.0
Requires-Dist: pydantic-settings>=2.0.2
Requires-Dist: pydantic>=2.1.1
Requires-Dist: sentry-sdk>=1
Requires-Dist: typer>=0.3.2
Requires-Dist: uvicorn>=0.13.3
Provides-Extra: extra
Requires-Dist: aiodns>=2.0.0; extra == 'extra'
Requires-Dist: aiohttp>=3.6.2; extra == 'extra'
Requires-Dist: bcrypt>=3.2.0; extra == 'extra'
Requires-Dist: ipython>=7.7.0; extra == 'extra'
Requires-Dist: requests>=2.24.0; extra == 'extra'
Requires-Dist: watchgod>=0.6; extra == 'extra'
